<?xml version="1.0"?>
<root>
  <item>
    <name>Mouse Bindings</name>

    <!-- External mouse config -->
    <item>
      <name>External mouse Config</name>
      <identifier>custom.external_mouse_config</identifier>
      <appendix>Mouse Back Button to Command + [</appendix>
      <appendix>Mouse Forward Button to Command + ]</appendix>
      <appendix>ScrollRight to Command + ]</appendix>

      <device_not>
        DeviceVendor::APPLE_COMPUTER,
        DeviceProduct::ANY
      </device_not>

      <!-- Mouse back button to "Back" -->
      <autogen>
        __PointingButtonToKey__
        PointingButton::BUTTON4, ModifierFlag::NONE,

        KeyCode::BRACKET_LEFT, ModifierFlag::COMMAND_L
      </autogen>

      <!-- Mouse forward button to "Forward" -->
      <autogen>
        __PointingButtonToKey__
        PointingButton::BUTTON5, ModifierFlag::NONE,

        KeyCode::BRACKET_RIGHT, ModifierFlag::COMMAND_L
      </autogen>

      <!-- Mouse scroll wheel right to "Forward" -->
      <autogen>
        __ScrollWheelToKey__
        ScrollWheel::RIGHT, ModifierFlag::NONE,

        KeyCode::BRACKET_RIGHT, ModifierFlag::COMMAND_L
      </autogen>
    </item>

    <!-- Emulate Linux-style "Hyper + Click" for moving/resizing. To be used in
         combination with Zooom2.

         Here, we use Fn as the movement modifier key for Zooom2 because it's
         the only one that doesn't come with any default functionality when
         combined with left-click.
    -->
    <item>
      <name>Zooom2 Support</name>
      <identifier>custom.zooom2_support</identifier>
      <appendix>Hyper + Left Click to Fn + Left Click</appendix>
      <appendix>Hyper + Right Click to Fn + Shift + Left Click</appendix>

      <!-- Hyper + Left Click to Fn + Left Click -->
      <autogen>
        __PointingButtonToPointingButton__
        PointingButton::LEFT,
        {{ MODIFIER_FLAG_HYPER }},

        PointingButton::LEFT,
        ModifierFlag::FN
      </autogen>

      <!-- Hyper + Right Click to Fn + Shift + Right Click -->
      <autogen>
        __PointingButtonToPointingButton__
        PointingButton::RIGHT,
        {{ MODIFIER_FLAG_HYPER }},

        PointingButton::LEFT,
        ModifierFlag::FN | ModifierFlag::SHIFT_L
      </autogen>
    </item>

    <!-- Control + Left Click emulates Right Click by default, which is really
         annoying. Here, we remap it to Command + Left Click instead, which is
         useful for opening links in new tabs in Chrome.
    -->
    <item>
      <name>Control + Left Click to Command + Left Click</name>
      <identifier>custom.control_left_click_to_command_left_click</identifier>

      <autogen>
        __PointingButtonToPointingButton__
        PointingButton::LEFT, ModifierFlag::CONTROL_L | ModifierFlag::NONE,
        PointingButton::LEFT, ModifierFlag::COMMAND_L
      </autogen>
    </item>
  </item>
</root>
